topsis_shreya/101903401.py
Topsis_Shreya_101903401-1.0.0.dist-info/LICENSE.txt
Topsis_Shreya_101903401-1.0.0.dist-info/METADATA
Topsis_Shreya_101903401-1.0.0.dist-info/WHEEL
Topsis_Shreya_101903401-1.0.0.dist-info/entry_points.txt
Topsis_Shreya_101903401-1.0.0.dist-info/top_level.txt
Topsis_Shreya_101903401-1.0.0.dist-info/RECORD
