Metadata-Version: 2.1
Name: Topsis-Shreya-101903401
Version: 1.0.0
Summary: Package to calculate topsis score and rank them
Home-page: https://github.com/shreyajha2410/topsis_shreya
Author: Shreya Jha
Author-email: shreyajha2418@gmail.com
License: MIT
Platform: UNKNOWN
Classifier: Programming Language :: Python :: 3
Classifier: License :: OSI Approved :: MIT License
Classifier: Operating System :: OS Independent
License-File: LICENSE.txt
Requires-Dist: pandas
